pgq/__init__.py
pgq/admin.py
pgq/apps.py
pgq/commands.py
pgq/decorators.py
pgq/exceptions.py
pgq/migrations/0001_initial.py
pgq/migrations/__init__.py
pgq/models.py
pgq/py.typed
pgq/queue.py
pgq/settings.py
mishka_queue-1.2.1.dist-info/LICENSE
mishka_queue-1.2.1.dist-info/WHEEL
mishka_queue-1.2.1.dist-info/METADATA
mishka_queue-1.2.1.dist-info/RECORD
