Metadata-Version: 2.1
Name: mishka-queue
Version: 1.2.1
Summary: Mishka Queue - A django task queue
License: BSD-2-Clause
Author: Ben Howes
Author-email: b.howes@neuronostics.com
Requires-Python: >=3.8,<4.0
Classifier: License :: OSI Approved :: BSD License
Classifier: Programming Language :: Python :: 3
Classifier: Programming Language :: Python :: 3.8
Classifier: Programming Language :: Python :: 3.9
Classifier: Programming Language :: Python :: 3.10
Requires-Dist: django (>=3.2)
